finq/__init__.py
finq/constants.py
finq/main.py
finq/typevars.py
test/__init__.py
test/test_any_none.py
test/test_cartesian.py
test/test_concat.py
test/test_constants.py
test/test_count_max_min_sum.py
test/test_distinct.py
test/test_enumerate.py
test/test_filter.py
test/test_first_list_set.py
test/test_flat_maps.py
test/test_flatten.py
test/test_foreach.py
test/test_group_by.py
test/test_join.py
test/test_map.py
test/test_pairs.py
test/test_peek.py
test/test_random.py
test/test_reduce.py
test/test_skip_take.py
test/test_sort.py
test/test_to_dict.py
test/test_zip.py
test/test_collections/__init__.py
FINQ-1.1.4.dist-info/LICENSE
FINQ-1.1.4.dist-info/METADATA
FINQ-1.1.4.dist-info/WHEEL
FINQ-1.1.4.dist-info/top_level.txt
FINQ-1.1.4.dist-info/RECORD
