Metadata-Version: 2.1
Name: FINQ
Version: 1.1.4
Summary: Lightweight conveyor data processing python framework
Home-page: https://github.com/FacelessLord/FINQ
Author: FacelessLord
Author-email: skyres21@gmail.com
License: UNKNOWN
Platform: UNKNOWN
Classifier: Programming Language :: Python :: 3
Classifier: License :: OSI Approved :: Apache Software License
Classifier: Operating System :: OS Independent
Requires-Python: >=3.6
